kde_ocl/__init__.py
kde_ocl/_ffi.py
kde_ocl/_ffi__ffi.py
kde_ocl/_ffi__lib.cp37-win_amd64.pyd
kde_ocl/gaussian_kde_ocl.py
kde_ocl-0.1.0.dist-info/LICENSE
kde_ocl-0.1.0.dist-info/METADATA
kde_ocl-0.1.0.dist-info/WHEEL
kde_ocl-0.1.0.dist-info/top_level.txt
kde_ocl-0.1.0.dist-info/RECORD
