Metadata-Version: 2.1
Name: kde-ocl
Version: 0.1.0
Summary: An OpenCL implementation of Kernel Density Estimation
Home-page: https://github.com/davenza/kde_ocl
Author: David Atienza
Author-email: datienza@fi.upm.es
License: UNKNOWN
Platform: any
Classifier: Programming Language :: Python :: 2.7
Classifier: Programming Language :: Python :: 3
Classifier: License :: OSI Approved :: MIT License
Classifier: Operating System :: OS Independent
Requires-Dist: milksnake
Requires-Dist: numpy
Requires-Dist: six
